<?xml version="1.0" encoding="utf-8"?>
<!-- Copyright (c) Microsoft Corporation. Licensed under the MIT License. See LICENSE in the project root for license information. -->
<Dependencies>
  <ProductDependencies>
    <Dependency Name="Microsoft.FrameworkUdk" Version="2.0.0-experimental-27200.1845.251215-1020.5">
      <Uri>https://dev.azure.com/microsoft/LiftedIXP/_git/DCPP</Uri>
      <Sha>547b4bb04a27a7e09e61022dc6ac3595fa1550f7</Sha>
    </Dependency>
    <Dependency Name="Microsoft.WindowsAppSDK.Foundation.TransportPackage" Version="2.0.0-20251224.1.nightly.internal">
      <Uri>https://dev.azure.com/microsoft/ProjectReunion/_git/WindowsAppSDK</Uri>
      <Sha>7bafcc2d5e3b80e2e1e0b0d160ec7e09cbe94a88</Sha>
    </Dependency>
    <Dependency Name="Microsoft.ProjectReunion.InteractiveExperiences.TransportPackage" Version="2.0.0-experimental-27200.1845.251215-1020.5">
      <Uri>https://dev.azure.com/microsoft/LiftedIXP/_git/DCPP</Uri>
      <Sha>547b4bb04a27a7e09e61022dc6ac3595fa1550f7</Sha>
    </Dependency>
    <!-- Closed source binary (ex PTLS and WinUIEdit) -->
    <Dependency Name="Microsoft.Internal.WinUIDetails" Version="2.10.0-experimental.20251229.0">
      <Uri>https://dev.azure.com/microsoft/ProjectReunion/_git/WindowsAppSDKClosed</Uri>
      <Sha>dd37af51755aee08e649a30d320f9570bceb4696</Sha>
    </Dependency>
    <Dependency Name="Microsoft.WindowsAppSDK.Base" Version="2.0.251128001-experimental">
      <Uri>https://dev.azure.com/microsoft/ProjectReunion/_git/WindowsAppSDKAggregator</Uri>
      <Sha>eda4bbdc05ddd6d1bc197ff930af59b4e50d891d</Sha>
    </Dependency>
    <Dependency Name="Microsoft.WindowsAppSDK.Foundation" Version="2.0.251224001-experimental">
      <Uri>https://dev.azure.com/microsoft/ProjectReunion/_git/WindowsAppSDK</Uri>
      <Sha>7bafcc2d5e3b80e2e1e0b0d160ec7e09cbe94a88</Sha>
    </Dependency>
    <Dependency Name="Microsoft.WindowsAppSDK.InteractiveExperiences" Version="2.0.5-experimental">
      <Uri>https://dev.azure.com/microsoft/LiftedIXP/_git/DCPP</Uri>
      <Sha>547b4bb04a27a7e09e61022dc6ac3595fa1550f7</Sha>
    </Dependency>
  </ProductDependencies>
  <ToolsetDependencies>
  </ToolsetDependencies>
</Dependencies>
